{
"type": "FeatureCollection",
"name": "HI_centroids",
"crs": { "type": "name", "properties": { "name": "urn:ogc:def:crs:EPSG::4269" } },
"features": [
{ "type": "Feature", "properties": { "GEOID": "15005" }, "geometry": { "type": "Point", "coordinates": [ -156.95836, 21.17883 ] } },
{ "type": "Feature", "properties": { "GEOID": "15003" }, "geometry": { "type": "Point", "coordinates": [ -157.97122, 21.45803 ] } },
{ "type": "Feature", "properties": { "GEOID": "15007" }, "geometry": { "type": "Point", "coordinates": [ -159.59668, 22.03935 ] } },
{ "type": "Feature", "properties": { "GEOID": "15001" }, "geometry": { "type": "Point", "coordinates": [ -155.52102, 19.60121 ] } },
{ "type": "Feature", "properties": { "GEOID": "15009" }, "geometry": { "type": "Point", "coordinates": [ -156.56891, 20.864 ] } }
]
}
